{
    "header": {
        "title": "Olmazor rayonı",
        "administration": "Hákimlik",
        "about": "Rayon haqqında",
        "council": "Mahalliy keńes",
        "information_service": "Aqparat xızmeti",
        "open_data": "Aşıq málimatlar",
        "contact": "Baylanıs",
        "selections": {
            "tasks": "Mánzıpler hám funksiyalar",
            "structure": "Uyımshıl tuzılıs",
            "leadership": "Basıwshılıq",
            "assistants": "Hákimnıń kómekshileri",
            "women_activist": "Háyellar faolları",
            "youth_leader": "Jaslar jetekshileri",
            "sectors": "Sektorlar",
            "reception_days": "Qawıl künderi",
            "district_history": "Rayonnıń tarixı",
            "council_deputies": "Keńes deputatları",
            "comissions": "Komissiyalar",
            "documents": "Jeke málimatlar",
            "news": "Jañalıqlar",
            "announcements": "Jarlıawlar",
            "projects": "Rayon proyektileri",
            "oav": "Aqparat quraldarı",
            "photo": "Foto galereya",
            "video": "Video galereya",
            "about_information": "Aqparat xızmeti haqqında",
            "tenders": "Tendelers",
            "corruption": "Korruptsiyalıq kúres",
            "investments": "Rayondaǵı investitsiyalar",
            "vacancies": "Bos iş orunları",
            "telegram": "Telegram",
            "instagram": "Instagram",
            "facebook": "Facebook",
            "email": "E-mail",
            "youtube": "YouTube",
            "twitter": "Twitter"
        }
    },
    "button": {
        "get_in_touch": "Baylanısıńız",
        "more_info": "Tolıǵıraq málimet",
        "read_more": "Kóbirek oqıń",
        "learn_more": "Kóbirek úyreniń",
        "apply_now": "Endi jasırıń",
        "view_all": "Bárliyn kóriw"
    },
    "projects": "Rayon proyektileri",
    "project_description": "Rayonnıń óz jaqsı ayaǵına shıqqan proyektileri",
    "teams": "Bizdiń jeme",
    "teams_description": "Rayonda óz isine jan síniwshi mamandar qızmet etedi",
    "events": "Sharalar",
    "latest_news": "Sońǵı jañalıqlar",
    "contact_us": "Bizben baylanısıńız",
    "contact_form": {
        "title": "Ótinishinizdi jiberińiz",
        "first_name": "Atı",
        "last_name": "Familiyası",
        "email_phone": "Email nemese Telefonnıń nomeri",
        "subject": "Mázún",
        "message": "Háber",
        "message_placeholder": "Bul jerge jazıń...",
        "submit": "Háberdi jiberiw"
    },
    "single_page": {
        "work_place": "Júmis orını : ",
        "birthday": "Tuwılǵan kún : ",
        "birth_place": "Tuwılǵan jer : ",
        "birthday_place": "Tuwılǵan jer hám sanası : ",
        "receptions": "Azamattardı qawıl etiw : ",
        "nationality": "Últtı : ",
        "position": "Qızmeti : ",
        "date": "Sana",
        "leader": "Baslıq : ",
        "address": "Manzil : "
    },
    "footer": {
        "usefull_links": "Paydalı siltemeler",
        "address": "Bizdiń manzilimiz",
        "quick_links": "Shuǵıl siltemeler",
        "follow_us": "Bizdi baqılańız",
        "home": "Bas bet",
        "about": "Turalı",
        "teams": "Jemeler",
        "events": "Sharalar",
        "news": "Jañalıqlar",
        "contact": "Bizben baylanısıńız"
    }
}
